{
  "annotations": {
    "list": [
      {
        "builtIn": 1,
        "datasource": "-- Grafana --",
        "enable": true,
        "hide": true,
        "iconColor": "rgba(0, 211, 255, 1)",
        "name": "Annotations & Alerts",
        "type": "dashboard"
      }
    ]
  },
  "editable": true,
  "gnetId": null,
  "graphTooltip": 0,
  "id": 1,
  "links": [],
  "panels": [
    {
      "cacheTimeout": null,
      "colorBackground": false,
      "colorPostfix": true,
      "colorPrefix": true,
      "colorValue": true,
      "colors": [
        "rgba(255, 43, 43, 0.97)",
        "#8AB8FF",
        "#8AB8FF"
      ],
      "datasource": null,
      "decimals": 1,
      "editable": true,
      "error": false,
      "format": "percent",
      "gauge": {
        "maxValue": 30,
        "minValue": 0,
        "show": false,
        "thresholdLabels": false,
        "thresholdMarkers": false
      },
      "gridPos": {
        "h": 4,
        "w": 7,
        "x": 0,
        "y": 0
      },
      "height": "",
      "id": 47,
      "interval": "",
      "isNew": true,
      "links": [],
      "mappingType": 1,
      "mappingTypes": [
        {
          "name": "value to text",
          "value": 1
        },
        {
          "name": "range to text",
          "value": 2
        }
      ],
      "maxDataPoints": 100,
      "nullPointMode": "connected",
      "nullText": null,
      "options": {},
      "postfix": "",
      "postfixFontSize": "20%",
      "prefix": "Humidity",
      "prefixFontSize": "70%",
      "rangeMaps": [
        {
          "from": "null",
          "text": "N/A",
          "to": "null"
        }
      ],
      "sparkline": {
        "fillColor": "rgba(34, 197, 16, 0.17)",
        "full": false,
        "lineColor": "rgb(30, 171, 15)",
        "show": false
      },
      "tableColumn": "",
      "targets": [
        {
          "alias": "",
          "dsType": "influxdb",
          "groupBy": [],
          "hide": false,
          "measurement": "Weather_Station",
          "orderByTime": "ASC",
          "policy": "default",
          "query": "SELECT last(\"temperature\") FROM \"yvr\" WHERE time > now() - 30m",
          "rawQuery": false,
          "refId": "A",
          "resultFormat": "time_series",
          "select": [
            [
              {
                "params": [
                  "RH"
                ],
                "type": "field"
              }
            ]
          ],
          "tags": []
        }
      ],
      "thresholds": "0,30,100",
      "timeFrom": null,
      "timeShift": null,
      "title": "Current Humidity",
      "type": "singlestat",
      "valueFontSize": "70%",
      "valueMaps": [
        {
          "op": "=",
          "text": "N/A",
          "value": "null"
        }
      ],
      "valueName": "current"
    },
    {
      "cacheTimeout": null,
      "colorBackground": false,
      "colorPostfix": true,
      "colorPrefix": true,
      "colorValue": true,
      "colors": [
        "#FF7383",
        "#FFB357",
        "#3274D9"
      ],
      "datasource": null,
      "decimals": 1,
      "editable": true,
      "error": false,
      "format": "celsius",
      "gauge": {
        "maxValue": 30,
        "minValue": 0,
        "show": false,
        "thresholdLabels": false,
        "thresholdMarkers": false
      },
      "gridPos": {
        "h": 4,
        "w": 7,
        "x": 7,
        "y": 0
      },
      "height": "",
      "id": 45,
      "interval": "",
      "isNew": true,
      "links": [],
      "mappingType": 1,
      "mappingTypes": [
        {
          "name": "value to text",
          "value": 1
        },
        {
          "name": "range to text",
          "value": 2
        }
      ],
      "maxDataPoints": 100,
      "nullPointMode": "connected",
      "nullText": null,
      "options": {},
      "postfix": "",
      "postfixFontSize": "20%",
      "prefix": "Temperature",
      "prefixFontSize": "70%",
      "rangeMaps": [
        {
          "from": "null",
          "text": "N/A",
          "to": "null"
        }
      ],
      "sparkline": {
        "fillColor": "rgba(34, 197, 16, 0.17)",
        "full": false,
        "lineColor": "rgb(30, 171, 15)",
        "show": false
      },
      "tableColumn": "",
      "targets": [
        {
          "alias": "",
          "dsType": "influxdb",
          "groupBy": [],
          "hide": false,
          "measurement": "Weather_Station",
          "orderByTime": "ASC",
          "policy": "default",
          "query": "SELECT last(\"temperature\") FROM \"yvr\" WHERE time > now() - 30m",
          "rawQuery": false,
          "refId": "A",
          "resultFormat": "time_series",
          "select": [
            [
              {
                "params": [
                  "Temperature"
                ],
                "type": "field"
              }
            ]
          ],
          "tags": []
        }
      ],
      "thresholds": "",
      "timeFrom": null,
      "timeShift": null,
      "title": "Current Temperature",
      "type": "singlestat",
      "valueFontSize": "70%",
      "valueMaps": [
        {
          "op": "=",
          "text": "N/A",
          "value": "null"
        }
      ],
      "valueName": "current"
    },
    {
      "bgColor": "rgb(102, 102, 102)",
      "clockType": "12 hour",
      "countdownSettings": {
        "customFormat": null,
        "endCountdownTime": "2019-03-29T16:11:00.000Z",
        "endText": "00:00:00"
      },
      "datasource": null,
      "dateSettings": {
        "dateFormat": "YYYY-MM-DD",
        "fontSize": "20px",
        "fontWeight": "bold",
        "showDate": true
      },
      "gridPos": {
        "h": 5,
        "w": 10,
        "x": 14,
        "y": 0
      },
      "id": 31,
      "links": [],
      "mode": "time",
      "offsetFromUtc": "",
      "offsetFromUtcMinutes": "",
      "options": {},
      "refreshSettings": {
        "syncWithDashboard": false
      },
      "targets": [
        {
          "groupBy": [
            {
              "params": [
                "$__interval"
              ],
              "type": "time"
            },
            {
              "params": [
                "null"
              ],
              "type": "fill"
            }
          ],
          "orderByTime": "ASC",
          "policy": "default",
          "refId": "A",
          "resultFormat": "time_series",
          "select": [
            [
              {
                "params": [
                  "value"
                ],
                "type": "field"
              },
              {
                "params": [],
                "type": "mean"
              }
            ]
          ],
          "tags": []
        }
      ],
      "timeSettings": {
        "customFormat": "HH:mm:ss",
        "fontSize": "50px",
        "fontWeight": "normal"
      },
      "timezone": "Africa/Tunis",
      "timezoneSettings": {
        "fontSize": "12px",
        "fontWeight": "normal",
        "showTimezone": true,
        "zoneFormat": "offsetAbbv"
      },
      "title": "Time",
      "type": "grafana-clock-panel"
    },
    {
      "datasource": null,
      "gridPos": {
        "h": 8,
        "w": 7,
        "x": 0,
        "y": 4
      },
      "id": 50,
      "links": [],
      "options": {
        "fieldOptions": {
          "calcs": [
            "mean"
          ],
          "defaults": {
            "mappings": [],
            "max": 100,
            "min": 0,
            "thresholds": [
              {
                "color": "green",
                "value": null
              },
              {
                "color": "super-light-red",
                "value": 0
              },
              {
                "color": "super-light-purple",
                "value": 25
              },
              {
                "color": "#6ED0E0",
                "value": 50
              },
              {
                "color": "semi-dark-blue",
                "value": 75
              },
              {
                "color": "dark-blue",
                "value": 100
              }
            ],
            "title": "Humidity",
            "unit": "humidity"
          },
          "override": {},
          "values": false
        },
        "orientation": "auto",
        "showThresholdLabels": true,
        "showThresholdMarkers": true
      },
      "pluginVersion": "6.5.1",
      "targets": [
        {
          "groupBy": [
            {
              "params": [
                "$__interval"
              ],
              "type": "time"
            },
            {
              "params": [
                "null"
              ],
              "type": "fill"
            }
          ],
          "measurement": "Weather_Station",
          "orderByTime": "ASC",
          "policy": "default",
          "refId": "A",
          "resultFormat": "time_series",
          "select": [
            [
              {
                "params": [
                  "RH"
                ],
                "type": "field"
              },
              {
                "params": [],
                "type": "mean"
              }
            ]
          ],
          "tags": []
        }
      ],
      "timeFrom": null,
      "timeShift": null,
      "title": "Humidity",
      "type": "gauge"
    },
    {
      "datasource": null,
      "gridPos": {
        "h": 8,
        "w": 7,
        "x": 7,
        "y": 4
      },
      "id": 52,
      "links": [],
      "options": {
        "fieldOptions": {
          "calcs": [
            "mean"
          ],
          "defaults": {
            "mappings": [],
            "max": 40,
            "min": -5,
            "thresholds": [
              {
                "color": "green",
                "value": null
              },
              {
                "color": "dark-blue",
                "value": -4
              },
              {
                "color": "light-blue",
                "value": 10
              },
              {
                "color": "super-light-blue",
                "value": 12
              },
              {
                "color": "super-light-orange",
                "value": 19
              },
              {
                "color": "super-light-red",
                "value": 25
              },
              {
                "color": "#E24D42",
                "value": 30
              },
              {
                "color": "dark-red",
                "value": 40
              }
            ],
            "title": "Temperature",
            "unit": "celsius"
          },
          "override": {},
          "values": false
        },
        "orientation": "auto",
        "showThresholdLabels": true,
        "showThresholdMarkers": true
      },
      "pluginVersion": "6.5.1",
      "targets": [
        {
          "groupBy": [
            {
              "params": [
                "$__interval"
              ],
              "type": "time"
            },
            {
              "params": [
                "null"
              ],
              "type": "fill"
            }
          ],
          "measurement": "Weather_Station",
          "orderByTime": "ASC",
          "policy": "default",
          "refId": "A",
          "resultFormat": "time_series",
          "select": [
            [
              {
                "params": [
                  "Temperature"
                ],
                "type": "field"
              },
              {
                "params": [],
                "type": "mean"
              }
            ]
          ],
          "tags": []
        }
      ],
      "timeFrom": null,
      "timeShift": null,
      "title": "Temperature",
      "type": "gauge"
    },
    {
      "cacheTimeout": null,
      "colorBackground": false,
      "colorValue": true,
      "colors": [
        "rgba(50, 172, 45, 0.97)",
        "rgba(237, 129, 40, 0.89)",
        "#508642"
      ],
      "datasource": null,
      "decimals": null,
      "editable": true,
      "error": false,
      "format": "velocitykmh",
      "gauge": {
        "maxValue": 110,
        "minValue": 0,
        "show": true,
        "thresholdLabels": false,
        "thresholdMarkers": true
      },
      "gridPos": {
        "h": 7,
        "w": 5,
        "x": 14,
        "y": 5
      },
      "id": 8,
      "interval": "1m",
      "links": [],
      "mappingType": 1,
      "mappingTypes": [
        {
          "name": "value to text",
          "value": 1
        },
        {
          "name": "range to text",
          "value": 2
        }
      ],
      "maxDataPoints": 100,
      "nullPointMode": "connected",
      "nullText": null,
      "options": {},
      "postfix": "",
      "postfixFontSize": "50%",
      "prefix": "",
      "prefixFontSize": "50%",
      "rangeMaps": [
        {
          "from": "null",
          "text": "N/A",
          "to": "null"
        }
      ],
      "sparkline": {
        "fillColor": "#7eb26d",
        "full": false,
        "lineColor": "rgb(31, 120, 193)",
        "show": false
      },
      "tableColumn": "",
      "targets": [
        {
          "dsType": "influxdb",
          "groupBy": [
            {
              "params": [
                "$interval"
              ],
              "type": "time"
            },
            {
              "params": [
                "null"
              ],
              "type": "fill"
            }
          ],
          "measurement": "Weather_Station",
          "orderByTime": "ASC",
          "policy": "default",
          "query": "SELECT max(\"windGust_kph\") FROM \"record\" WHERE time > now() - 10m GROUP BY time(1m) fill(null)",
          "rawQuery": false,
          "refId": "A",
          "resultFormat": "time_series",
          "select": [
            [
              {
                "params": [
                  "speed5"
                ],
                "type": "field"
              },
              {
                "params": [],
                "type": "mean"
              }
            ]
          ],
          "tags": []
        }
      ],
      "thresholds": "",
      "title": "Wind gust Average (5 min)",
      "type": "singlestat",
      "valueFontSize": "70%",
      "valueMaps": [
        {
          "op": "=",
          "text": "N/A",
          "value": "null"
        }
      ],
      "valueName": "avg"
    },
    {
      "cacheTimeout": null,
      "colorBackground": false,
      "colorPostfix": false,
      "colorPrefix": false,
      "colorValue": true,
      "colors": [
        "rgba(50, 172, 45, 0.97)",
        "rgba(237, 129, 40, 0.89)",
        "#badff4"
      ],
      "datasource": null,
      "editable": true,
      "error": false,
      "format": "none",
      "gauge": {
        "maxValue": 360,
        "minValue": 0,
        "show": true,
        "thresholdLabels": true,
        "thresholdMarkers": true
      },
      "gridPos": {
        "h": 7,
        "w": 5,
        "x": 19,
        "y": 5
      },
      "id": 5,
      "interval": null,
      "links": [],
      "mappingType": 2,
      "mappingTypes": [
        {
          "name": "value to text",
          "value": 1
        },
        {
          "name": "range to text",
          "value": 2
        }
      ],
      "maxDataPoints": 100,
      "nullPointMode": "connected",
      "nullText": null,
      "options": {},
      "postfix": "",
      "postfixFontSize": "50%",
      "prefix": "",
      "prefixFontSize": "50%",
      "rangeMaps": [
        {
          "from": "45",
          "text": "E",
          "to": "135"
        },
        {
          "from": "135",
          "text": "S",
          "to": "225"
        },
        {
          "from": "225",
          "text": "W",
          "to": "315"
        },
        {
          "from": "315",
          "text": "N",
          "to": "360"
        },
        {
          "from": "0",
          "text": "N",
          "to": "45"
        }
      ],
      "sparkline": {
        "fillColor": "rgba(31, 118, 189, 0.18)",
        "full": false,
        "lineColor": "rgb(31, 120, 193)",
        "show": true
      },
      "tableColumn": "",
      "targets": [
        {
          "alias": "Wind Direction",
          "dsType": "influxdb",
          "groupBy": [
            {
              "params": [
                "$interval"
              ],
              "type": "time"
            },
            {
              "params": [
                "null"
              ],
              "type": "fill"
            }
          ],
          "measurement": "Weather_Station",
          "orderByTime": "ASC",
          "policy": "default",
          "query": "SELECT last(\"windDir\") FROM \"record\"",
          "rawQuery": false,
          "refId": "A",
          "resultFormat": "time_series",
          "select": [
            [
              {
                "params": [
                  "direction"
                ],
                "type": "field"
              },
              {
                "params": [],
                "type": "last"
              }
            ]
          ],
          "tags": []
        }
      ],
      "thresholds": "",
      "title": "Direction du vent",
      "type": "singlestat",
      "valueFontSize": "70%",
      "valueMaps": [
        {
          "op": "=",
          "text": "N/A",
          "value": ""
        }
      ],
      "valueName": "avg"
    },
    {
      "cacheTimeout": null,
      "colorBackground": false,
      "colorValue": true,
      "colors": [
        "rgba(50, 172, 45, 0.97)",
        "#70dbed",
        "#f2c96d"
      ],
      "datasource": null,
      "decimals": null,
      "editable": true,
      "error": false,
      "format": "lengthmm",
      "gauge": {
        "maxValue": 5000,
        "minValue": 0,
        "show": true,
        "thresholdLabels": true,
        "thresholdMarkers": true
      },
      "gridPos": {
        "h": 6,
        "w": 6,
        "x": 0,
        "y": 12
      },
      "id": 12,
      "interval": null,
      "links": [],
      "mappingType": 1,
      "mappingTypes": [
        {
          "name": "value to text",
          "value": 1
        },
        {
          "name": "range to text",
          "value": 2
        }
      ],
      "maxDataPoints": 100,
      "nullPointMode": "connected",
      "nullText": null,
      "options": {},
      "postfix": "",
      "postfixFontSize": "20%",
      "prefix": "",
      "prefixFontSize": "50%",
      "rangeMaps": [
        {
          "from": "null",
          "text": "N/A",
          "to": "null"
        }
      ],
      "sparkline": {
        "fillColor": "#629e51",
        "full": true,
        "lineColor": "#64b0c8",
        "show": false
      },
      "tableColumn": "",
      "targets": [
        {
          "groupBy": [
            {
              "params": [
                "$__interval"
              ],
              "type": "time"
            },
            {
              "params": [
                "null"
              ],
              "type": "fill"
            }
          ],
          "hide": false,
          "measurement": "Weather_Station",
          "orderByTime": "ASC",
          "policy": "default",
          "refId": "B",
          "resultFormat": "time_series",
          "select": [
            [
              {
                "params": [
                  "rainfall24"
                ],
                "type": "field"
              },
              {
                "params": [],
                "type": "last"
              }
            ]
          ],
          "tags": []
        }
      ],
      "thresholds": "",
      "title": "Pluie actuelle (24 heures)",
      "type": "singlestat",
      "valueFontSize": "70%",
      "valueMaps": [
        {
          "op": "=",
          "text": "N/A",
          "value": "null"
        }
      ],
      "valueName": "current"
    },
    {
      "aliasColors": {},
      "bars": false,
      "dashLength": 10,
      "dashes": false,
      "datasource": null,
      "editable": true,
      "error": false,
      "fill": 0,
      "fillGradient": 0,
      "grid": {},
      "gridPos": {
        "h": 6,
        "w": 12,
        "x": 6,
        "y": 12
      },
      "hiddenSeries": false,
      "id": 33,
      "legend": {
        "avg": false,
        "current": true,
        "max": true,
        "min": true,
        "show": true,
        "total": false,
        "values": true
      },
      "lines": true,
      "linewidth": 2,
      "links": [],
      "nullPointMode": "connected",
      "options": {
        "dataLinks": []
      },
      "percentage": false,
      "pointradius": 5,
      "points": false,
      "renderer": "flot",
      "seriesOverrides": [
        {
          "alias": "/^Temp/",
          "color": "#BF1B00",
          "yaxis": 1,
          "zindex": 3
        },
        {
          "alias": "/^Humi/",
          "yaxis": 2
        },
        {
          "alias": "maxTemp",
          "color": "#BF1B00",
          "fillBelowTo": "minTemp",
          "legend": false,
          "lines": false
        },
        {
          "alias": "minTemp",
          "color": "#BF1B00",
          "legend": false,
          "lines": false
        }
      ],
      "spaceLength": 10,
      "stack": false,
      "steppedLine": false,
      "targets": [
        {
          "alias": "Temp",
          "dsType": "influxdb",
          "groupBy": [
            {
              "params": [
                "5m"
              ],
              "type": "time"
            }
          ],
          "hide": false,
          "measurement": "Weather_Station",
          "orderByTime": "ASC",
          "policy": "autogen",
          "query": "SELECT mean(\"value\") FROM \"wxt_value\" WHERE \"instance\" = '46.234.46.52-4001' AND \"type_instance\" = 'temp_air' AND $timeFilter GROUP BY time($interval)",
          "rawQuery": false,
          "refId": "A",
          "resultFormat": "time_series",
          "select": [
            [
              {
                "params": [
                  "Temperature"
                ],
                "type": "field"
              },
              {
                "params": [],
                "type": "mean"
              }
            ]
          ],
          "tags": []
        },
        {
          "alias": "Humi",
          "dsType": "influxdb",
          "groupBy": [
            {
              "params": [
                "$__interval"
              ],
              "type": "time"
            }
          ],
          "hide": false,
          "measurement": "Weather_Station",
          "orderByTime": "ASC",
          "policy": "default",
          "query": "SELECT mean(\"value\") FROM \"wxt_value\" WHERE \"instance\" = '46.234.46.52-4001' AND \"type_instance\" = 'humi_air' AND $timeFilter GROUP BY time($interval)",
          "rawQuery": false,
          "refId": "B",
          "resultFormat": "time_series",
          "select": [
            [
              {
                "params": [
                  "RH"
                ],
                "type": "field"
              },
              {
                "params": [],
                "type": "mean"
              }
            ]
          ],
          "tags": []
        },
        {
          "alias": "maxTemp",
          "dsType": "influxdb",
          "groupBy": [
            {
              "params": [
                "auto"
              ],
              "type": "time"
            }
          ],
          "hide": false,
          "measurement": "Weather_Station",
          "orderByTime": "ASC",
          "policy": "default",
          "query": "SELECT max(\"value\") FROM \"wxt_value\" WHERE \"instance\" = '46.234.46.52-4001' AND \"type_instance\" = 'temp_air' AND $timeFilter GROUP BY time($interval)",
          "rawQuery": false,
          "refId": "C",
          "resultFormat": "time_series",
          "select": [
            [
              {
                "params": [
                  "Temperature"
                ],
                "type": "field"
              },
              {
                "params": [],
                "type": "max"
              }
            ]
          ],
          "tags": []
        },
        {
          "alias": "minTemp",
          "dsType": "influxdb",
          "groupBy": [
            {
              "params": [
                "auto"
              ],
              "type": "time"
            }
          ],
          "hide": false,
          "measurement": "Weather_Station",
          "orderByTime": "ASC",
          "policy": "default",
          "query": "SELECT min(\"value\") FROM \"wxt_value\" WHERE \"instance\" = '46.234.46.52-4001' AND \"type_instance\" = 'temp_air' AND $timeFilter GROUP BY time($interval)",
          "rawQuery": false,
          "refId": "D",
          "resultFormat": "time_series",
          "select": [
            [
              {
                "params": [
                  "Temperature"
                ],
                "type": "field"
              },
              {
                "params": [],
                "type": "min"
              }
            ]
          ],
          "tags": []
        }
      ],
      "thresholds": [],
      "timeFrom": null,
      "timeRegions": [],
      "timeShift": null,
      "title": "Temperatur / Humidity",
      "tooltip": {
        "msResolution": true,
        "shared": true,
        "sort": 0,
        "value_type": "cumulative"
      },
      "type": "graph",
      "xaxis": {
        "buckets": null,
        "mode": "time",
        "name": null,
        "show": true,
        "values": []
      },
      "yaxes": [
        {
          "format": "celsius",
          "label": "Temp",
          "logBase": 1,
          "max": null,
          "min": null,
          "show": true
        },
        {
          "format": "humidity",
          "label": "Humi",
          "logBase": 1,
          "max": 100,
          "min": 0,
          "show": true
        }
      ],
      "yaxis": {
        "align": false,
        "alignLevel": null
      }
    },
    {
      "aliasColors": {
        "record.mean": "#E5A8E2",
        "record.wind_dir": "#6ED0E0",
        "record.wind_gust_dir": "#D683CE"
      },
      "bars": false,
      "dashLength": 10,
      "dashes": false,
      "datasource": null,
      "editable": true,
      "error": false,
      "fill": 1,
      "fillGradient": 0,
      "grid": {},
      "gridPos": {
        "h": 6,
        "w": 6,
        "x": 18,
        "y": 12
      },
      "hiddenSeries": false,
      "id": 9,
      "legend": {
        "avg": false,
        "current": false,
        "max": false,
        "min": false,
        "show": false,
        "total": false,
        "values": false
      },
      "lines": true,
      "linewidth": 1,
      "links": [],
      "nullPointMode": "connected",
      "options": {
        "dataLinks": []
      },
      "percentage": false,
      "pointradius": 5,
      "points": false,
      "renderer": "flot",
      "seriesOverrides": [
        {
          "alias": "Wind Direction",
          "color": "#dedaf7",
          "fill": 2,
          "lines": true,
          "linewidth": 2
        }
      ],
      "spaceLength": 10,
      "stack": false,
      "steppedLine": false,
      "targets": [
        {
          "alias": "Wind Direction",
          "dsType": "influxdb",
          "groupBy": [
            {
              "params": [
                "$interval"
              ],
              "type": "time"
            },
            {
              "params": [
                "null"
              ],
              "type": "fill"
            }
          ],
          "measurement": "Weather_Station",
          "orderByTime": "ASC",
          "policy": "default",
          "refId": "A",
          "resultFormat": "time_series",
          "select": [
            [
              {
                "params": [
                  "direction"
                ],
                "type": "field"
              },
              {
                "params": [],
                "type": "mean"
              },
              {
                "params": [
                  "direction"
                ],
                "type": "alias"
              }
            ]
          ],
          "tags": []
        }
      ],
      "thresholds": [],
      "timeFrom": null,
      "timeRegions": [],
      "timeShift": null,
      "title": "Direction du vent",
      "tooltip": {
        "msResolution": false,
        "shared": true,
        "sort": 0,
        "value_type": "cumulative"
      },
      "type": "graph",
      "xaxis": {
        "buckets": null,
        "mode": "time",
        "name": null,
        "show": true,
        "values": []
      },
      "yaxes": [
        {
          "format": "degree",
          "label": null,
          "logBase": 1,
          "max": 360,
          "min": 0,
          "show": true
        },
        {
          "format": "short",
          "label": null,
          "logBase": 1,
          "max": null,
          "min": null,
          "show": false
        }
      ],
      "yaxis": {
        "align": false,
        "alignLevel": null
      }
    },
    {
      "aliasColors": {
        "Rainfall Inches": "#1F78C1",
        "record.mean": "#1F78C1",
        "record.sum": "#1F78C1"
      },
      "bars": true,
      "dashLength": 10,
      "dashes": false,
      "datasource": null,
      "editable": true,
      "error": false,
      "fill": 1,
      "fillGradient": 0,
      "grid": {},
      "gridPos": {
        "h": 7,
        "w": 6,
        "x": 0,
        "y": 18
      },
      "hiddenSeries": false,
      "id": 6,
      "interval": "1h",
      "legend": {
        "avg": false,
        "current": true,
        "max": false,
        "min": false,
        "show": true,
        "total": true,
        "values": true
      },
      "lines": false,
      "linewidth": 2,
      "links": [],
      "nullPointMode": "connected",
      "options": {
        "dataLinks": []
      },
      "percentage": false,
      "pointradius": 5,
      "points": false,
      "renderer": "flot",
      "seriesOverrides": [],
      "spaceLength": 10,
      "stack": false,
      "steppedLine": false,
      "targets": [
        {
          "alias": "mm de pluie",
          "dsType": "influxdb",
          "groupBy": [
            {
              "params": [
                "$interval"
              ],
              "type": "time"
            },
            {
              "params": [
                "null"
              ],
              "type": "fill"
            }
          ],
          "measurement": "Weather_Station",
          "orderByTime": "ASC",
          "policy": "default",
          "refId": "A",
          "resultFormat": "time_series",
          "select": [
            [
              {
                "params": [
                  "rainfall"
                ],
                "type": "field"
              },
              {
                "params": [],
                "type": "sum"
              }
            ]
          ],
          "tags": []
        }
      ],
      "thresholds": [],
      "timeFrom": null,
      "timeRegions": [],
      "timeShift": null,
      "title": "Pluie /H",
      "tooltip": {
        "msResolution": false,
        "shared": true,
        "sort": 0,
        "value_type": "cumulative"
      },
      "type": "graph",
      "xaxis": {
        "buckets": null,
        "mode": "time",
        "name": null,
        "show": true,
        "values": []
      },
      "yaxes": [
        {
          "format": "lengthmm",
          "label": "",
          "logBase": 1,
          "max": null,
          "min": 0,
          "show": true
        },
        {
          "format": "short",
          "label": "",
          "logBase": 1,
          "max": null,
          "min": null,
          "show": true
        }
      ],
      "yaxis": {
        "align": false,
        "alignLevel": null
      }
    },
    {
      "aliasColors": {
        "Predicted Temperature": "#3F6833",
        "Temperature": "#9AC48A",
        "record.mean": "#7EB26D"
      },
      "bars": false,
      "dashLength": 10,
      "dashes": false,
      "datasource": null,
      "decimals": 1,
      "editable": true,
      "error": false,
      "fill": 1,
      "fillGradient": 0,
      "grid": {},
      "gridPos": {
        "h": 7,
        "w": 9,
        "x": 6,
        "y": 18
      },
      "hiddenSeries": false,
      "id": 1,
      "legend": {
        "alignAsTable": true,
        "avg": false,
        "current": true,
        "max": true,
        "min": true,
        "rightSide": false,
        "show": true,
        "total": false,
        "values": true
      },
      "lines": true,
      "linewidth": 1,
      "links": [],
      "nullPointMode": "connected",
      "options": {
        "dataLinks": []
      },
      "percentage": false,
      "pointradius": 5,
      "points": false,
      "renderer": "flot",
      "seriesOverrides": [
        {
          "alias": "Outside Temperature",
          "color": "#f4d598",
          "fill": 3,
          "lines": true,
          "linewidth": 2
        }
      ],
      "spaceLength": 10,
      "stack": false,
      "steppedLine": false,
      "targets": [
        {
          "alias": "Outside Temperature",
          "dsType": "influxdb",
          "groupBy": [
            {
              "params": [
                "$interval"
              ],
              "type": "time"
            },
            {
              "params": [
                "null"
              ],
              "type": "fill"
            }
          ],
          "hide": false,
          "measurement": "Weather_Station",
          "orderByTime": "ASC",
          "policy": "default",
          "refId": "A",
          "resultFormat": "time_series",
          "select": [
            [
              {
                "params": [
                  "Temperature"
                ],
                "type": "field"
              },
              {
                "params": [],
                "type": "mean"
              }
            ]
          ],
          "tags": []
        }
      ],
      "thresholds": [],
      "timeFrom": null,
      "timeRegions": [],
      "timeShift": null,
      "title": "Outside Temperature",
      "tooltip": {
        "msResolution": false,
        "shared": false,
        "sort": 0,
        "value_type": "cumulative"
      },
      "type": "graph",
      "xaxis": {
        "buckets": null,
        "mode": "time",
        "name": null,
        "show": true,
        "values": [
          "total"
        ]
      },
      "yaxes": [
        {
          "format": "celsius",
          "label": "",
          "logBase": 1,
          "max": null,
          "min": null,
          "show": true
        },
        {
          "format": "celsius",
          "label": null,
          "logBase": 1,
          "max": null,
          "min": null,
          "show": true
        }
      ],
      "yaxis": {
        "align": false,
        "alignLevel": null
      }
    },
    {
      "aliasColors": {
        "Predicted Temperature": "#3F6833",
        "Temperature": "#9AC48A",
        "record.mean": "#7EB26D"
      },
      "bars": false,
      "dashLength": 10,
      "dashes": false,
      "datasource": null,
      "decimals": 1,
      "editable": true,
      "error": false,
      "fill": 1,
      "fillGradient": 0,
      "grid": {},
      "gridPos": {
        "h": 7,
        "w": 9,
        "x": 15,
        "y": 18
      },
      "hiddenSeries": false,
      "id": 48,
      "legend": {
        "alignAsTable": true,
        "avg": false,
        "current": true,
        "max": true,
        "min": true,
        "rightSide": false,
        "show": true,
        "total": false,
        "values": true
      },
      "lines": true,
      "linewidth": 1,
      "links": [],
      "nullPointMode": "connected",
      "options": {
        "dataLinks": []
      },
      "percentage": false,
      "pointradius": 5,
      "points": false,
      "renderer": "flot",
      "seriesOverrides": [
        {
          "alias": "Outside Humidity",
          "color": "#1F60C4",
          "fill": 3,
          "lines": true,
          "linewidth": 2
        }
      ],
      "spaceLength": 10,
      "stack": false,
      "steppedLine": false,
      "targets": [
        {
          "alias": "Outside Humidity",
          "dsType": "influxdb",
          "groupBy": [
            {
              "params": [
                "$interval"
              ],
              "type": "time"
            },
            {
              "params": [
                "null"
              ],
              "type": "fill"
            }
          ],
          "hide": false,
          "measurement": "Weather_Station",
          "orderByTime": "ASC",
          "policy": "default",
          "refId": "A",
          "resultFormat": "time_series",
          "select": [
            [
              {
                "params": [
                  "RH"
                ],
                "type": "field"
              },
              {
                "params": [],
                "type": "last"
              }
            ]
          ],
          "tags": []
        }
      ],
      "thresholds": [],
      "timeFrom": null,
      "timeRegions": [],
      "timeShift": null,
      "title": "Outside Humidity",
      "tooltip": {
        "msResolution": false,
        "shared": false,
        "sort": 0,
        "value_type": "cumulative"
      },
      "type": "graph",
      "xaxis": {
        "buckets": null,
        "mode": "time",
        "name": null,
        "show": true,
        "values": [
          "total"
        ]
      },
      "yaxes": [
        {
          "format": "celsius",
          "label": "",
          "logBase": 1,
          "max": null,
          "min": null,
          "show": true
        },
        {
          "format": "celsius",
          "label": null,
          "logBase": 1,
          "max": null,
          "min": null,
          "show": true
        }
      ],
      "yaxis": {
        "align": false,
        "alignLevel": null
      }
    },
    {
      "aliasColors": {},
      "bars": false,
      "dashLength": 10,
      "dashes": false,
      "datasource": null,
      "fill": 5,
      "fillGradient": 0,
      "gridPos": {
        "h": 7,
        "w": 6,
        "x": 0,
        "y": 25
      },
      "hiddenSeries": false,
      "id": 18,
      "legend": {
        "alignAsTable": true,
        "avg": false,
        "current": false,
        "max": true,
        "min": true,
        "rightSide": false,
        "show": true,
        "total": false,
        "values": true
      },
      "lines": true,
      "linewidth": 3,
      "links": [
        {
          "url": "/"
        }
      ],
      "nullPointMode": "null",
      "options": {
        "dataLinks": []
      },
      "percentage": false,
      "pointradius": 1,
      "points": false,
      "renderer": "flot",
      "seriesOverrides": [],
      "spaceLength": 10,
      "stack": false,
      "steppedLine": false,
      "targets": [
        {
          "alias": "Puissance solaire",
          "dsType": "influxdb",
          "groupBy": [
            {
              "params": [
                "$__interval"
              ],
              "type": "time"
            },
            {
              "params": [
                "none"
              ],
              "type": "fill"
            }
          ],
          "measurement": "Weather_Station",
          "orderByTime": "ASC",
          "policy": "default",
          "refId": "A",
          "resultFormat": "time_series",
          "select": [
            [
              {
                "params": [
                  "Temperature"
                ],
                "type": "field"
              },
              {
                "params": [],
                "type": "last"
              }
            ]
          ],
          "tags": []
        }
      ],
      "thresholds": [],
      "timeFrom": null,
      "timeRegions": [],
      "timeShift": null,
      "title": "Radiation solaire",
      "tooltip": {
        "shared": false,
        "sort": 0,
        "value_type": "cumulative"
      },
      "type": "graph",
      "xaxis": {
        "buckets": null,
        "mode": "time",
        "name": null,
        "show": true,
        "values": []
      },
      "yaxes": [
        {
          "format": "short",
          "label": "",
          "logBase": 1,
          "max": null,
          "min": null,
          "show": true
        },
        {
          "format": "short",
          "label": null,
          "logBase": 1,
          "max": null,
          "min": null,
          "show": false
        }
      ],
      "yaxis": {
        "align": false,
        "alignLevel": null
      }
    },
    {
      "columns": [
        {
          "text": "Count",
          "value": "count"
        }
      ],
      "datasource": null,
      "fontSize": "100%",
      "gridPos": {
        "h": 7,
        "w": 8,
        "x": 6,
        "y": 25
      },
      "id": 39,
      "links": [],
      "options": {},
      "pageSize": null,
      "scroll": true,
      "showHeader": true,
      "sort": {
        "col": 0,
        "desc": true
      },
      "styles": [
        {
          "dateFormat": "YYYY-MM-DD HH:mm:ss",
          "pattern": "Time",
          "type": "date"
        },
        {
          "colorMode": "cell",
          "colors": [
            "#8AB8FF",
            "rgba(237, 129, 40, 0.89)",
            "#B877D9"
          ],
          "decimals": 0,
          "pattern": "/.*/",
          "thresholds": [],
          "type": "number",
          "unit": "velocitykmh"
        }
      ],
      "targets": [
        {
          "alias": "Wind Speed",
          "dimensions": "coloName",
          "filters": [
            {
              "key": "responseCode",
              "operator": "=",
              "value": "NXDOMAIN"
            }
          ],
          "from": "zone",
          "groupBy": [
            {
              "params": [
                "3m"
              ],
              "type": "time"
            },
            {
              "params": [
                "null"
              ],
              "type": "fill"
            }
          ],
          "measurement": "Weather_Station",
          "metrics": [
            "queryCount"
          ],
          "orderByTime": "ASC",
          "policy": "autogen",
          "refId": "A",
          "resultFormat": "time_series",
          "select": [
            [
              {
                "params": [
                  "speed"
                ],
                "type": "field"
              },
              {
                "params": [],
                "type": "mean"
              }
            ]
          ],
          "tag": "$zone",
          "tags": []
        }
      ],
      "title": "WIND Speed",
      "transform": "timeseries_to_rows",
      "type": "table"
    },
    {
      "aliasColors": {},
      "bars": true,
      "dashLength": 10,
      "dashes": false,
      "datasource": null,
      "fill": 8,
      "fillGradient": 0,
      "gridPos": {
        "h": 7,
        "w": 10,
        "x": 14,
        "y": 25
      },
      "hiddenSeries": false,
      "id": 29,
      "legend": {
        "avg": false,
        "current": false,
        "max": false,
        "min": false,
        "show": true,
        "total": false,
        "values": false
      },
      "lines": true,
      "linewidth": 3,
      "links": [],
      "nullPointMode": "null",
      "options": {
        "dataLinks": []
      },
      "percentage": false,
      "pointradius": 5,
      "points": false,
      "renderer": "flot",
      "seriesOverrides": [],
      "spaceLength": 10,
      "stack": false,
      "steppedLine": true,
      "targets": [
        {
          "alias": "Qté de pluie du jour",
          "groupBy": [
            {
              "params": [
                "$__interval"
              ],
              "type": "time"
            },
            {
              "params": [
                "null"
              ],
              "type": "fill"
            }
          ],
          "measurement": "Weather_Station",
          "orderByTime": "ASC",
          "policy": "default",
          "refId": "A",
          "resultFormat": "time_series",
          "select": [
            [
              {
                "params": [
                  "rainfall"
                ],
                "type": "field"
              },
              {
                "params": [],
                "type": "mean"
              }
            ]
          ],
          "tags": []
        }
      ],
      "thresholds": [],
      "timeFrom": null,
      "timeRegions": [],
      "timeShift": null,
      "title": "Pluie du jour",
      "tooltip": {
        "shared": true,
        "sort": 0,
        "value_type": "individual"
      },
      "type": "graph",
      "xaxis": {
        "buckets": null,
        "mode": "time",
        "name": null,
        "show": true,
        "values": []
      },
      "yaxes": [
        {
          "format": "lengthmm",
          "label": "",
          "logBase": 1,
          "max": null,
          "min": null,
          "show": true
        },
        {
          "format": "short",
          "label": null,
          "logBase": 1,
          "max": null,
          "min": null,
          "show": true
        }
      ],
      "yaxis": {
        "align": false,
        "alignLevel": null
      }
    },
    {
      "aliasColors": {
        "Avg": "#BA43A9"
      },
      "bars": false,
      "dashLength": 10,
      "dashes": false,
      "datasource": null,
      "editable": true,
      "error": false,
      "fill": 1,
      "fillGradient": 0,
      "grid": {},
      "gridPos": {
        "h": 7,
        "w": 11,
        "x": 0,
        "y": 32
      },
      "hiddenSeries": false,
      "id": 37,
      "legend": {
        "alignAsTable": true,
        "avg": false,
        "current": true,
        "max": false,
        "min": false,
        "rightSide": true,
        "show": true,
        "sort": null,
        "sortDesc": null,
        "total": false,
        "values": true
      },
      "lines": true,
      "linewidth": 1,
      "links": [],
      "nullPointMode": "connected",
      "options": {
        "dataLinks": []
      },
      "percentage": false,
      "pointradius": 5,
      "points": false,
      "renderer": "flot",
      "seriesOverrides": [
        {
          "alias": "Max",
          "color": "#890F02",
          "fillBelowTo": "Min"
        },
        {
          "alias": "Avg",
          "zindex": 2
        },
        {
          "alias": "Min",
          "color": "#0A437C"
        },
        {
          "alias": "Min"
        },
        {
          "alias": "1h",
          "color": "#E24D42",
          "linewidth": 2,
          "zindex": 3
        }
      ],
      "spaceLength": 10,
      "stack": false,
      "steppedLine": false,
      "targets": [
        {
          "alias": "Avg",
          "dsType": "influxdb",
          "groupBy": [
            {
              "params": [
                "auto"
              ],
              "type": "time"
            }
          ],
          "measurement": "Weather_Station",
          "orderByTime": "ASC",
          "policy": "default",
          "query": "SELECT mean(\"value\") FROM \"wxt_value\" WHERE (\"instance\" = '46.234.46.52-4001' AND \"type_instance\" = 'wind_dir_avg') AND $timeFilter GROUP BY time($__interval)",
          "rawQuery": false,
          "refId": "A",
          "resultFormat": "time_series",
          "select": [
            [
              {
                "params": [
                  "direction"
                ],
                "type": "field"
              },
              {
                "params": [],
                "type": "mean"
              }
            ]
          ],
          "tags": []
        },
        {
          "alias": "Max",
          "dsType": "influxdb",
          "groupBy": [
            {
              "params": [
                "auto"
              ],
              "type": "time"
            }
          ],
          "measurement": "Weather_Station",
          "orderByTime": "ASC",
          "policy": "default",
          "query": "SELECT max(\"value\") FROM \"wxt_value\" WHERE \"instance\" = '46.234.46.52-4001' AND \"type_instance\" = 'wind_dir_max' AND $timeFilter GROUP BY time($interval)",
          "refId": "B",
          "resultFormat": "time_series",
          "select": [
            [
              {
                "params": [
                  "direction"
                ],
                "type": "field"
              },
              {
                "params": [],
                "type": "max"
              }
            ]
          ],
          "tags": []
        },
        {
          "alias": "1h",
          "dsType": "influxdb",
          "groupBy": [
            {
              "params": [
                "15m"
              ],
              "type": "time"
            }
          ],
          "hide": false,
          "measurement": "Weather_Station",
          "orderByTime": "ASC",
          "policy": "default",
          "query": "SELECT median(\"value\") FROM \"wxt_value\" WHERE \"instance\" = '46.234.46.52-4001' AND \"type_instance\" = 'wind_dir_avg' AND $timeFilter GROUP BY time(1h)",
          "refId": "D",
          "resultFormat": "time_series",
          "select": [
            [
              {
                "params": [
                  "direction"
                ],
                "type": "field"
              },
              {
                "params": [],
                "type": "median"
              }
            ]
          ],
          "tags": []
        }
      ],
      "thresholds": [],
      "timeFrom": null,
      "timeRegions": [],
      "timeShift": null,
      "title": "Wind direction",
      "tooltip": {
        "msResolution": true,
        "shared": true,
        "sort": 0,
        "value_type": "cumulative"
      },
      "type": "graph",
      "xaxis": {
        "buckets": null,
        "mode": "time",
        "name": null,
        "show": true,
        "values": []
      },
      "yaxes": [
        {
          "format": "degree",
          "logBase": 1,
          "max": 360,
          "min": 0,
          "show": true
        },
        {
          "format": "short",
          "logBase": 1,
          "max": null,
          "min": null,
          "show": true
        }
      ],
      "yaxis": {
        "align": false,
        "alignLevel": null
      }
    },
    {
      "aliasColors": {},
      "bars": false,
      "dashLength": 10,
      "dashes": false,
      "datasource": null,
      "editable": true,
      "error": false,
      "fill": 3,
      "fillGradient": 0,
      "grid": {},
      "gridPos": {
        "h": 7,
        "w": 13,
        "x": 11,
        "y": 32
      },
      "hiddenSeries": false,
      "id": 35,
      "legend": {
        "alignAsTable": true,
        "avg": true,
        "current": true,
        "max": true,
        "min": false,
        "rightSide": true,
        "show": true,
        "total": false,
        "values": true
      },
      "lines": true,
      "linewidth": 3,
      "links": [],
      "nullPointMode": "connected",
      "options": {
        "dataLinks": []
      },
      "percentage": false,
      "pointradius": 5,
      "points": false,
      "renderer": "flot",
      "seriesOverrides": [
        {
          "alias": "mean",
          "linewidth": 2
        },
        {
          "alias": "max",
          "color": "#0A50A1",
          "fillBelowTo": "min",
          "lines": false,
          "zindex": -3
        },
        {
          "alias": "wind_speed_min",
          "color": "#447EBC",
          "zindex": -3
        },
        {
          "alias": "wind_speed_min",
          "linewidth": 2
        },
        {
          "alias": "mean 5 Min",
          "steppedLine": true
        },
        {
          "alias": "min",
          "lines": false
        }
      ],
      "spaceLength": 10,
      "stack": false,
      "steppedLine": false,
      "targets": [
        {
          "alias": "speed",
          "dsType": "influxdb",
          "groupBy": [
            {
              "interval": "auto",
              "params": [
                "auto"
              ],
              "type": "time"
            }
          ],
          "measurement": "Weather_Station",
          "orderByTime": "ASC",
          "policy": "default",
          "query": "SELECT mean(\"value\") AS \"value\" FROM \"wxt_value\" WHERE \"instance\" = '46.234.46.52-4001' AND \"type_instance\" = 'wind_speed_avg' AND $timeFilter GROUP BY time($interval), type_instance",
          "rawQuery": false,
          "refId": "A",
          "resultFormat": "time_series",
          "select": [
            [
              {
                "params": [
                  "speed"
                ],
                "type": "field"
              },
              {
                "params": [],
                "type": "mean"
              }
            ]
          ],
          "tags": []
        },
        {
          "alias": "min",
          "dsType": "influxdb",
          "groupBy": [
            {
              "interval": "auto",
              "params": [
                "auto"
              ],
              "type": "time"
            }
          ],
          "measurement": "Weather_Station",
          "orderByTime": "ASC",
          "policy": "default",
          "query": "SELECT min(\"value\") AS \"value\" FROM \"wxt_value\" WHERE \"instance\" = '46.234.46.52-4001' AND \"type_instance\" = 'wind_speed_min' AND $timeFilter GROUP BY time($interval), type_instance",
          "rawQuery": false,
          "refId": "B",
          "resultFormat": "time_series",
          "select": [
            [
              {
                "params": [
                  "speed"
                ],
                "type": "field"
              },
              {
                "params": [],
                "type": "min"
              }
            ]
          ],
          "tags": []
        },
        {
          "alias": "max",
          "dsType": "influxdb",
          "groupBy": [
            {
              "interval": "auto",
              "params": [
                "auto"
              ],
              "type": "time"
            }
          ],
          "measurement": "Weather_Station",
          "orderByTime": "ASC",
          "policy": "default",
          "query": "SELECT max(\"value\") AS \"value\" FROM \"wxt_value\" WHERE \"instance\" = '46.234.46.52-4001' AND \"type_instance\" = 'wind_speed_max' AND $timeFilter GROUP BY time($interval), type_instance",
          "rawQuery": false,
          "refId": "C",
          "resultFormat": "time_series",
          "select": [
            [
              {
                "params": [
                  "speed"
                ],
                "type": "field"
              },
              {
                "params": [],
                "type": "max"
              }
            ]
          ],
          "tags": []
        },
        {
          "alias": "speed 5 Min",
          "dsType": "influxdb",
          "groupBy": [
            {
              "interval": "auto",
              "params": [
                "auto"
              ],
              "type": "time"
            }
          ],
          "measurement": "Weather_Station",
          "orderByTime": "ASC",
          "policy": "default",
          "query": "SELECT median(\"value\") AS \"value\" FROM \"wxt_value\" WHERE \"instance\" = '46.234.46.52-4001' AND \"type_instance\" = 'wind_speed_avg' AND $timeFilter GROUP BY time(1h), type_instance",
          "rawQuery": false,
          "refId": "D",
          "resultFormat": "time_series",
          "select": [
            [
              {
                "params": [
                  "speed5"
                ],
                "type": "field"
              },
              {
                "params": [],
                "type": "mean"
              }
            ]
          ],
          "tags": []
        }
      ],
      "thresholds": [],
      "timeFrom": null,
      "timeRegions": [],
      "timeShift": null,
      "title": "Wind Speed",
      "tooltip": {
        "msResolution": true,
        "shared": true,
        "sort": 0,
        "value_type": "cumulative"
      },
      "type": "graph",
      "xaxis": {
        "buckets": null,
        "mode": "time",
        "name": null,
        "show": true,
        "values": []
      },
      "yaxes": [
        {
          "format": "velocitykmh",
          "logBase": 1,
          "max": null,
          "min": null,
          "show": true
        },
        {
          "format": "short",
          "logBase": 1,
          "max": null,
          "min": null,
          "show": true
        }
      ],
      "yaxis": {
        "align": false,
        "alignLevel": null
      }
    }
  ],
  "refresh": "30s",
  "schemaVersion": 21,
  "style": "dark",
  "tags": [],
  "templating": {
    "list": []
  },
  "time": {
    "from": "now-24h",
    "to": "now"
  },
  "timepicker": {
    "refresh_intervals": [
      "30s",
      "5m",
      "30m",
      "1h",
      "1d"
    ],
    "time_options": [
      "5m",
      "15m",
      "1h",
      "6h",
      "12h",
      "24h",
      "2d",
      "7d",
      "30d"
    ]
  },
  "timezone": "browser",
  "title": "Weather_Station",
  "uid": "000000003",
  "version": 45
}